LICENCE
MANIFEST.in
README.rst
setup.py
django_le_twitter.egg-info/PKG-INFO
django_le_twitter.egg-info/SOURCES.txt
django_le_twitter.egg-info/dependency_links.txt
django_le_twitter.egg-info/not-zip-safe
django_le_twitter.egg-info/requires.txt
django_le_twitter.egg-info/top_level.txt
le_twitter/__init__.py
le_twitter/views.py