Metadata-Version: 1.0
Name: django-le-twitter
Version: 0.2
Summary: Twitter authentication that sucks
Home-page: https://github.com/brutasse/django-le-twitter
Author: Bruno Renie
Author-email: bruno@renie.fr
License: BSD licence, see LICENCE file
Platform: UNKNOWN
Classifier: Development Status :: 3 - Alpha
Classifier: Environment :: Web Environment
Classifier: Framework :: Django
Classifier: Intended Audience :: Developers
Classifier: License :: OSI Approved :: BSD License
Classifier: Natural Language :: English
Classifier: Programming Language :: Python
